{"artist":"Jakob Jennerholm Hammar","title":"Weaving Drafts at the Edge of the Abyss","slug":"weaving-drafts-at-the-edge-of-the-abyss","form":"Talk / Demo + Q&A","desc":"A series of experimental explorations into digital weaving drafts/notation. The project is founded on a series of vague questions about time, nature, relationality and pattern-making which are engaged with through the creation of generative and interactive digital and physical weaving drafts.","imgur":"Z84HQD1","url":"https://jennerholmhammar.info/project/weaving-drafts/","website":"https://jennerholmhammar.info","instagram":"knoegle","twitter":"","facebook":""}